pisco/__init__.py
pisco/__main__.py
pisco/application.py
pisco/input_output/__init__.py
pisco/input_output/backlight.py
pisco/input_output/http_image.py
pisco/input_output/sonos_device.py
pisco/user_interface/__init__.py
pisco/user_interface/command_line_interface.py
pisco/user_interface/graphical_user_interface.py
pisco-0.6.1.dist-info/LICENSE
pisco-0.6.1.dist-info/METADATA
pisco-0.6.1.dist-info/WHEEL
pisco-0.6.1.dist-info/entry_points.txt
pisco-0.6.1.dist-info/RECORD
