Metadata-Version: 2.1
Name: pisco
Version: 0.6.1
Summary: Keyboard-only controller for Sonos speakers
Home-page: https://github.com/christophgietl/pisco
License: MIT
Author: Christoph Gietl
Author-email: christophgietl@users.noreply.github.com
Requires-Python: >=3.9,<4.0
Classifier: License :: OSI Approved :: MIT License
Classifier: Programming Language :: Python :: 3
Classifier: Programming Language :: Python :: 3.9
Classifier: Programming Language :: Python :: 3.10
Classifier: Programming Language :: Python :: 3.11
Classifier: Programming Language :: Python :: 3.12
Requires-Dist: Pillow (>=10.1,<11.0)
Requires-Dist: click (>=8.1,<9.0)
Requires-Dist: python-json-logger (>=2.0,<3.0)
Requires-Dist: soco (>=0.30,<0.31)
Requires-Dist: xdg (>=6.0,<7.0)
Project-URL: Repository, https://github.com/christophgietl/pisco
